{"config":{"output_file":null,"full_docs":false,"pub_only":false,"reachable_only":false,"distro_crate":false,"signatures":false,"borrow_data":false},"version":"0.19.0","compilation":{"directory":"/home/mrmjt/60DaysOfCoding/RUST/Runner-Up","program":"/home/mrmjt/.rustup/toolchains/stable-x86_64-unknown-linux-gnu/bin/rls","arguments":[],"output":"/home/mrmjt/60DaysOfCoding/RUST/Runner-Up/target/rls/debug/deps/libRunner_Up-b619ac2f05213635.rmeta"},"prelude":{"crate_id":{"name":"Runner_Up","disambiguator":[14962096931836712438,11008159529520732139]},"crate_root":"src","external_crates":[{"file_name":"/home/mrmjt/60DaysOfCoding/RUST/Runner-Up/src/main.rs","num":1,"id":{"name":"std","disambiguator":[5726307116676674259,9254205407228129584]}},{"file_name":"/home/mrmjt/60DaysOfCoding/RUST/Runner-Up/src/main.rs","num":2,"id":{"name":"core","disambiguator":[13299148613267607203,8249913267494127673]}},{"file_name":"/home/mrmjt/60DaysOfCoding/RUST/Runner-Up/src/main.rs","num":3,"id":{"name":"compiler_builtins","disambiguator":[197050223691728347,13453459908300789634]}},{"file_name":"/home/mrmjt/60DaysOfCoding/RUST/Runner-Up/src/main.rs","num":4,"id":{"name":"rustc_std_workspace_core","disambiguator":[7068544857341867760,4986237062560097230]}},{"file_name":"/home/mrmjt/60DaysOfCoding/RUST/Runner-Up/src/main.rs","num":5,"id":{"name":"alloc","disambiguator":[18278181253470956455,5630036847974018351]}},{"file_name":"/home/mrmjt/60DaysOfCoding/RUST/Runner-Up/src/main.rs","num":6,"id":{"name":"libc","disambiguator":[14314454188171778451,16107994531515979130]}},{"file_name":"/home/mrmjt/60DaysOfCoding/RUST/Runner-Up/src/main.rs","num":7,"id":{"name":"unwind","disambiguator":[14027036961787401129,9740892787592816042]}},{"file_name":"/home/mrmjt/60DaysOfCoding/RUST/Runner-Up/src/main.rs","num":8,"id":{"name":"hashbrown","disambiguator":[9151246664428058867,3149456407424329247]}},{"file_name":"/home/mrmjt/60DaysOfCoding/RUST/Runner-Up/src/main.rs","num":9,"id":{"name":"rustc_std_workspace_alloc","disambiguator":[5378796546799943917,291117324214328413]}},{"file_name":"/home/mrmjt/60DaysOfCoding/RUST/Runner-Up/src/main.rs","num":10,"id":{"name":"rustc_demangle","disambiguator":[14457926311222789857,2794564911830687161]}},{"file_name":"/home/mrmjt/60DaysOfCoding/RUST/Runner-Up/src/main.rs","num":11,"id":{"name":"backtrace_sys","disambiguator":[16727297303745515064,14497453895406869387]}},{"file_name":"/home/mrmjt/60DaysOfCoding/RUST/Runner-Up/src/main.rs","num":12,"id":{"name":"panic_unwind","disambiguator":[11013963231826958606,13465865664615988446]}},{"file_name":"/home/mrmjt/60DaysOfCoding/RUST/Runner-Up/src/main.rs","num":13,"id":{"name":"test","disambiguator":[5765054934864926401,2639923181651054695]}},{"file_name":"/home/mrmjt/60DaysOfCoding/RUST/Runner-Up/src/main.rs","num":14,"id":{"name":"getopts","disambiguator":[2098548642306959476,4503562345541869532]}},{"file_name":"/home/mrmjt/60DaysOfCoding/RUST/Runner-Up/src/main.rs","num":15,"id":{"name":"unicode_width","disambiguator":[10856762353680266435,9633175732998463656]}},{"file_name":"/home/mrmjt/60DaysOfCoding/RUST/Runner-Up/src/main.rs","num":16,"id":{"name":"term","disambiguator":[1093731378681898757,1908147581576966143]}}],"span":{"file_name":"src/main.rs","byte_start":0,"byte_end":986,"line_start":1,"line_end":49,"column_start":1,"column_end":2}},"imports":[{"kind":"Use","ref_id":{"krate":1,"index":2148},"span":{"file_name":"src/main.rs","byte_start":9,"byte_end":11,"line_start":1,"line_end":1,"column_start":10,"column_end":12},"alias_span":null,"name":"io","value":"","parent":{"krate":0,"index":0}}],"defs":[{"kind":"Mod","id":{"krate":0,"index":0},"span":{"file_name":"src/main.rs","byte_start":0,"byte_end":986,"line_start":1,"line_end":49,"column_start":1,"column_end":2},"name":"","qualname":"::","value":"src/main.rs","parent":null,"children":[{"krate":0,"index":10},{"krate":0,"index":11},{"krate":0,"index":12},{"krate":0,"index":13},{"krate":0,"index":14},{"krate":0,"index":15}],"decl_id":null,"docs":"","sig":null,"attributes":[]},{"kind":"Function","id":{"krate":0,"index":13},"span":{"file_name":"src/main.rs","byte_start":17,"byte_end":21,"line_start":3,"line_end":3,"column_start":4,"column_end":8},"name":"main","qualname":"::main","value":"fn () -> ()","parent":null,"children":[],"decl_id":null,"docs":"","sig":null,"attributes":[{"value":"allow(dead_code)","span":{"file_name":"src/main.rs","byte_start":0,"byte_end":0,"line_start":1,"line_end":1,"column_start":1,"column_end":1}}]},{"kind":"Local","id":{"krate":0,"index":4294967276},"span":{"file_name":"src/main.rs","byte_start":79,"byte_end":83,"line_start":5,"line_end":5,"column_start":13,"column_end":17},"name":"list","qualname":"list$19","value":"std::vec::Vec<i32>","parent":null,"children":[],"decl_id":null,"docs":"","sig":null,"attributes":[]},{"kind":"Local","id":{"krate":0,"index":4294967274},"span":{"file_name":"src/main.rs","byte_start":106,"byte_end":107,"line_start":6,"line_end":6,"column_start":13,"column_end":14},"name":"x","qualname":"x$21","value":"std::string::String","parent":null,"children":[],"decl_id":null,"docs":"","sig":null,"attributes":[]},{"kind":"Local","id":{"krate":0,"index":4294967259},"span":{"file_name":"src/main.rs","byte_start":169,"byte_end":170,"line_start":8,"line_end":8,"column_start":9,"column_end":10},"name":"x","qualname":"x$36","value":"&str","parent":null,"children":[],"decl_id":null,"docs":"","sig":null,"attributes":[]},{"kind":"Local","id":{"krate":0,"index":4294967254},"span":{"file_name":"src/main.rs","byte_start":189,"byte_end":190,"line_start":9,"line_end":9,"column_start":9,"column_end":10},"name":"i","qualname":"i$41","value":"usize","parent":null,"children":[],"decl_id":null,"docs":"","sig":null,"attributes":[]},{"kind":"Local","id":{"krate":0,"index":4294967245},"span":{"file_name":"src/main.rs","byte_start":214,"byte_end":215,"line_start":10,"line_end":10,"column_start":9,"column_end":10},"name":"y","qualname":"y$50","value":"&str","parent":null,"children":[],"decl_id":null,"docs":"","sig":null,"attributes":[]},{"kind":"Local","id":{"krate":0,"index":4294967232},"span":{"file_name":"src/main.rs","byte_start":239,"byte_end":240,"line_start":11,"line_end":11,"column_start":9,"column_end":10},"name":"y","qualname":"y$63","value":"i32","parent":null,"children":[],"decl_id":null,"docs":"","sig":null,"attributes":[]},{"kind":"Local","id":{"krate":0,"index":4294967215},"span":{"file_name":"src/main.rs","byte_start":374,"byte_end":377,"line_start":16,"line_end":16,"column_start":9,"column_end":12},"name":"max","qualname":"max$80","value":"i32","parent":null,"children":[],"decl_id":null,"docs":"","sig":null,"attributes":[]},{"kind":"Local","id":{"krate":0,"index":4294967198},"span":{"file_name":"src/main.rs","byte_start":632,"byte_end":633,"line_start":27,"line_end":27,"column_start":9,"column_end":10},"name":"i","qualname":"i$97","value":"usize","parent":null,"children":[],"decl_id":null,"docs":"","sig":null,"attributes":[]},{"kind":"Local","id":{"krate":0,"index":4294967170},"span":{"file_name":"src/main.rs","byte_start":773,"byte_end":776,"line_start":35,"line_end":35,"column_start":9,"column_end":12},"name":"max","qualname":"max$125","value":"i32","parent":null,"children":[],"decl_id":null,"docs":"","sig":null,"attributes":[]},{"kind":"Local","id":{"krate":0,"index":4294967161},"span":{"file_name":"src/main.rs","byte_start":835,"byte_end":836,"line_start":40,"line_end":40,"column_start":12,"column_end":13},"name":"a","qualname":"::longest::a","value":"&std::vec::Vec<i32>","parent":null,"children":[],"decl_id":null,"docs":"","sig":null,"attributes":[]},{"kind":"Function","id":{"krate":0,"index":14},"span":{"file_name":"src/main.rs","byte_start":827,"byte_end":834,"line_start":40,"line_end":40,"column_start":4,"column_end":11},"name":"longest","qualname":"::longest","value":"fn (a: &Vec<i32>) -> i32","parent":null,"children":[],"decl_id":null,"docs":"","sig":null,"attributes":[]},{"kind":"Local","id":{"krate":0,"index":4294967150},"span":{"file_name":"src/main.rs","byte_start":870,"byte_end":877,"line_start":41,"line_end":41,"column_start":13,"column_end":20},"name":"longest","qualname":"longest$145","value":"i32","parent":null,"children":[],"decl_id":null,"docs":"","sig":null,"attributes":[]},{"kind":"Local","id":{"krate":0,"index":4294967144},"span":{"file_name":"src/main.rs","byte_start":894,"byte_end":895,"line_start":42,"line_end":42,"column_start":10,"column_end":11},"name":"i","qualname":"i$151","value":"i32","parent":null,"children":[],"decl_id":null,"docs":"","sig":null,"attributes":[]}],"impls":[],"refs":[{"kind":"Mod","span":{"file_name":"src/main.rs","byte_start":4,"byte_end":7,"line_start":1,"line_end":1,"column_start":5,"column_end":8},"ref_id":{"krate":1,"index":0}},{"kind":"Function","span":{"file_name":"src/main.rs","byte_start":118,"byte_end":121,"line_start":6,"line_end":6,"column_start":25,"column_end":28},"ref_id":{"krate":5,"index":3293}},{"kind":"Type","span":{"file_name":"src/main.rs","byte_start":110,"byte_end":116,"line_start":6,"line_end":6,"column_start":17,"column_end":23},"ref_id":{"krate":5,"index":4679}},{"kind":"Function","span":{"file_name":"src/main.rs","byte_start":141,"byte_end":150,"line_start":7,"line_end":7,"column_start":17,"column_end":26},"ref_id":{"krate":1,"index":2646}},{"kind":"Function","span":{"file_name":"src/main.rs","byte_start":133,"byte_end":138,"line_start":7,"line_end":7,"column_start":9,"column_end":14},"ref_id":{"krate":1,"index":2640}},{"kind":"Mod","span":{"file_name":"src/main.rs","byte_start":129,"byte_end":131,"line_start":7,"line_end":7,"column_start":5,"column_end":7},"ref_id":{"krate":1,"index":2148}},{"kind":"Variable","span":{"file_name":"src/main.rs","byte_start":157,"byte_end":158,"line_start":7,"line_end":7,"column_start":33,"column_end":34},"ref_id":{"krate":0,"index":4294967274}},{"kind":"Function","span":{"file_name":"src/main.rs","byte_start":173,"byte_end":177,"line_start":8,"line_end":8,"column_start":13,"column_end":17},"ref_id":{"krate":2,"index":6238}},{"kind":"Variable","span":{"file_name":"src/main.rs","byte_start":171,"byte_end":172,"line_start":8,"line_end":8,"column_start":11,"column_end":12},"ref_id":{"krate":0,"index":4294967274}},{"kind":"Function","span":{"file_name":"src/main.rs","byte_start":199,"byte_end":202,"line_start":9,"line_end":9,"column_start":19,"column_end":22},"ref_id":{"krate":2,"index":6160}},{"kind":"Variable","span":{"file_name":"src/main.rs","byte_start":197,"byte_end":198,"line_start":9,"line_end":9,"column_start":17,"column_end":18},"ref_id":{"krate":0,"index":4294967259}},{"kind":"Variable","span":{"file_name":"src/main.rs","byte_start":219,"byte_end":220,"line_start":10,"line_end":10,"column_start":14,"column_end":15},"ref_id":{"krate":0,"index":4294967259}},{"kind":"Variable","span":{"file_name":"src/main.rs","byte_start":221,"byte_end":222,"line_start":10,"line_end":10,"column_start":16,"column_end":17},"ref_id":{"krate":0,"index":4294967254}},{"kind":"Variable","span":{"file_name":"src/main.rs","byte_start":224,"byte_end":225,"line_start":10,"line_end":10,"column_start":19,"column_end":20},"ref_id":{"krate":0,"index":4294967254}},{"kind":"Function","span":{"file_name":"src/main.rs","byte_start":258,"byte_end":264,"line_start":11,"line_end":11,"column_start":28,"column_end":34},"ref_id":{"krate":2,"index":4592}},{"kind":"Function","span":{"file_name":"src/main.rs","byte_start":250,"byte_end":255,"line_start":11,"line_end":11,"column_start":20,"column_end":25},"ref_id":{"krate":2,"index":6261}},{"kind":"Variable","span":{"file_name":"src/main.rs","byte_start":248,"byte_end":249,"line_start":11,"line_end":11,"column_start":18,"column_end":19},"ref_id":{"krate":0,"index":4294967245}},{"kind":"Function","span":{"file_name":"src/main.rs","byte_start":277,"byte_end":281,"line_start":12,"line_end":12,"column_start":10,"column_end":14},"ref_id":{"krate":5,"index":3596}},{"kind":"Variable","span":{"file_name":"src/main.rs","byte_start":272,"byte_end":276,"line_start":12,"line_end":12,"column_start":5,"column_end":9},"ref_id":{"krate":0,"index":4294967276}},{"kind":"Variable","span":{"file_name":"src/main.rs","byte_start":282,"byte_end":283,"line_start":12,"line_end":12,"column_start":15,"column_end":16},"ref_id":{"krate":0,"index":4294967232}},{"kind":"Function","span":{"file_name":"src/main.rs","byte_start":380,"byte_end":387,"line_start":16,"line_end":16,"column_start":15,"column_end":22},"ref_id":{"krate":0,"index":14}},{"kind":"Variable","span":{"file_name":"src/main.rs","byte_start":389,"byte_end":393,"line_start":16,"line_end":16,"column_start":24,"column_end":28},"ref_id":{"krate":0,"index":4294967276}},{"kind":"Variable","span":{"file_name":"src/main.rs","byte_start":571,"byte_end":574,"line_start":25,"line_end":25,"column_start":11,"column_end":14},"ref_id":{"krate":0,"index":4294967215}},{"kind":"Function","span":{"file_name":"src/main.rs","byte_start":578,"byte_end":585,"line_start":25,"line_end":25,"column_start":18,"column_end":25},"ref_id":{"krate":0,"index":14}},{"kind":"Variable","span":{"file_name":"src/main.rs","byte_start":587,"byte_end":591,"line_start":25,"line_end":25,"column_start":27,"column_end":31},"ref_id":{"krate":0,"index":4294967276}},{"kind":"Function","span":{"file_name":"src/main.rs","byte_start":647,"byte_end":650,"line_start":27,"line_end":27,"column_start":24,"column_end":27},"ref_id":{"krate":5,"index":3603}},{"kind":"Variable","span":{"file_name":"src/main.rs","byte_start":642,"byte_end":646,"line_start":27,"line_end":27,"column_start":19,"column_end":23},"ref_id":{"krate":0,"index":4294967276}},{"kind":"Variable","span":{"file_name":"src/main.rs","byte_start":666,"byte_end":669,"line_start":28,"line_end":28,"column_start":12,"column_end":15},"ref_id":{"krate":0,"index":4294967215}},{"kind":"Variable","span":{"file_name":"src/main.rs","byte_start":673,"byte_end":677,"line_start":28,"line_end":28,"column_start":19,"column_end":23},"ref_id":{"krate":0,"index":4294967276}},{"kind":"Variable","span":{"file_name":"src/main.rs","byte_start":678,"byte_end":679,"line_start":28,"line_end":28,"column_start":24,"column_end":25},"ref_id":{"krate":0,"index":4294967198}},{"kind":"Function","span":{"file_name":"src/main.rs","byte_start":699,"byte_end":705,"line_start":29,"line_end":29,"column_start":18,"column_end":24},"ref_id":{"krate":5,"index":3586}},{"kind":"Variable","span":{"file_name":"src/main.rs","byte_start":694,"byte_end":698,"line_start":29,"line_end":29,"column_start":13,"column_end":17},"ref_id":{"krate":0,"index":4294967276}},{"kind":"Variable","span":{"file_name":"src/main.rs","byte_start":706,"byte_end":707,"line_start":29,"line_end":29,"column_start":25,"column_end":26},"ref_id":{"krate":0,"index":4294967198}},{"kind":"Function","span":{"file_name":"src/main.rs","byte_start":779,"byte_end":786,"line_start":35,"line_end":35,"column_start":15,"column_end":22},"ref_id":{"krate":0,"index":14}},{"kind":"Variable","span":{"file_name":"src/main.rs","byte_start":788,"byte_end":792,"line_start":35,"line_end":35,"column_start":24,"column_end":28},"ref_id":{"krate":0,"index":4294967276}},{"kind":"Variable","span":{"file_name":"src/main.rs","byte_start":811,"byte_end":814,"line_start":36,"line_end":36,"column_start":17,"column_end":20},"ref_id":{"krate":0,"index":4294967170}},{"kind":"Type","span":{"file_name":"src/main.rs","byte_start":840,"byte_end":843,"line_start":40,"line_end":40,"column_start":17,"column_end":20},"ref_id":{"krate":5,"index":3563}},{"kind":"Variable","span":{"file_name":"src/main.rs","byte_start":879,"byte_end":880,"line_start":41,"line_end":41,"column_start":22,"column_end":23},"ref_id":{"krate":0,"index":4294967161}},{"kind":"Function","span":{"file_name":"src/main.rs","byte_start":901,"byte_end":905,"line_start":42,"line_end":42,"column_start":17,"column_end":21},"ref_id":{"krate":2,"index":4928}},{"kind":"Variable","span":{"file_name":"src/main.rs","byte_start":899,"byte_end":900,"line_start":42,"line_end":42,"column_start":15,"column_end":16},"ref_id":{"krate":0,"index":4294967161}},{"kind":"Variable","span":{"file_name":"src/main.rs","byte_start":921,"byte_end":922,"line_start":44,"line_end":44,"column_start":12,"column_end":13},"ref_id":{"krate":0,"index":4294967144}},{"kind":"Variable","span":{"file_name":"src/main.rs","byte_start":923,"byte_end":930,"line_start":44,"line_end":44,"column_start":14,"column_end":21},"ref_id":{"krate":0,"index":4294967150}},{"kind":"Variable","span":{"file_name":"src/main.rs","byte_start":944,"byte_end":951,"line_start":45,"line_end":45,"column_start":13,"column_end":20},"ref_id":{"krate":0,"index":4294967150}},{"kind":"Variable","span":{"file_name":"src/main.rs","byte_start":954,"byte_end":955,"line_start":45,"line_end":45,"column_start":23,"column_end":24},"ref_id":{"krate":0,"index":4294967144}},{"kind":"Variable","span":{"file_name":"src/main.rs","byte_start":977,"byte_end":984,"line_start":48,"line_end":48,"column_start":5,"column_end":12},"ref_id":{"krate":0,"index":4294967150}}],"macro_refs":[],"relations":[]}